rtfcre-2.0.1.dist-info/METADATA
rtfcre-2.0.1.dist-info/WHEEL
rtfcre/__init__.py
rtfcre/rtfcre.pyd
rtfcre-2.0.1.dist-info/RECORD
