Metadata-Version: 2.1
Name: rtfcre
Version: 2.0.1
Classifier: Programming Language :: Python :: Implementation :: CPython
Classifier: Programming Language :: Python :: 3.7
Classifier: Programming Language :: Python :: 3.8
Classifier: Programming Language :: Python :: 3.9
Summary: Python library for Rich Text Format with Court Reporting Extensions (RTF/CRE) dictionaries
Home-Page: https://github.com/sammdot/rtfcre
Author: Sammi De Guzman <sammi@sammdot.ca>
Author-email: Sammi De Guzman <sammi@sammdot.ca>
